cricscraper/__init__.py
cricscraper/cricinfo.py
cricscraper/cricsheet.py
cricscraper/matchinfo.py
python_cricket_scraper-0.1.2.dist-info/LICENSE
python_cricket_scraper-0.1.2.dist-info/METADATA
python_cricket_scraper-0.1.2.dist-info/WHEEL
python_cricket_scraper-0.1.2.dist-info/top_level.txt
python_cricket_scraper-0.1.2.dist-info/zip-safe
python_cricket_scraper-0.1.2.dist-info/RECORD
