Metadata-Version: 2.1
Name: python-cricket-scraper
Version: 0.1.2
Summary: python-cricket-scraper is built to get cricket data from Cricsheet and ESPNCricInfo
Home-page: https://github.com/kakdeykaushik/python-cricket-scraper
Author: Kaushik Kakdey
Author-email: kaushik.kakdey@gmail.com
License: MIT
Project-URL: Bug Tracker, https://github.com/kakdeykaushik/python-cricket-scraper/issues
Keywords: espncricinfo cricket t20 odi test cricsheet
Platform: UNKNOWN
Classifier: Programming Language :: Python :: 3
Classifier: License :: OSI Approved :: MIT License
Classifier: Development Status :: 5 - Production/Stable
Classifier: Operating System :: OS Independent
Requires-Dist: numpy
Requires-Dist: pandas
Requires-Dist: pyyaml
Requires-Dist: requests
